series.py
jie-1.0.0.dist-info/METADATA
jie-1.0.0.dist-info/WHEEL
jie-1.0.0.dist-info/top_level.txt
jie-1.0.0.dist-info/RECORD
