Metadata-Version: 2.1
Name: jie
Version: 1.0.0
Summary: 递归法实现斐波那契数列
Home-page: UNKNOWN
Author: zj-1225
Author-email: 3183631339@qq.com
License: MIT
Keywords: helper
Platform: UNKNOWN
Requires-Python: >=3
Requires-Dist: scapy (>=2.4.4)
Requires-Dist: psutil (>=5.8.0)
